MANIFEST.in
README.rst
setup.py
bootstrapform/__init__.py
bootstrapform/config.py
bootstrapform/meta.py
bootstrapform/models.py
bootstrapform/tests.py
bootstrapform/templates/bootstrapform/field.html
bootstrapform/templates/bootstrapform/form.html
bootstrapform/templates/bootstrapform/formset.html
bootstrapform/templatetags/__init__.py
bootstrapform/templatetags/bootstrap.py
django_bootstrap_form_tkliuxing.egg-info/PKG-INFO
django_bootstrap_form_tkliuxing.egg-info/SOURCES.txt
django_bootstrap_form_tkliuxing.egg-info/dependency_links.txt
django_bootstrap_form_tkliuxing.egg-info/not-zip-safe
django_bootstrap_form_tkliuxing.egg-info/requires.txt
django_bootstrap_form_tkliuxing.egg-info/top_level.txt